openadapt_privacy/__init__.py
openadapt_privacy/base.py
openadapt_privacy/config.py
openadapt_privacy/loaders.py
openadapt_privacy/pipelines/__init__.py
openadapt_privacy/pipelines/dicts.py
openadapt_privacy/providers/__init__.py
openadapt_privacy/providers/presidio.py
openadapt_privacy-0.1.1.dist-info/METADATA
openadapt_privacy-0.1.1.dist-info/WHEEL
openadapt_privacy-0.1.1.dist-info/RECORD
