Metadata-Version: 2.4
Name: openadapt-privacy
Version: 0.1.1
Summary: Privacy scrubbing for GUI automation data - PII/PHI detection and redaction
Project-URL: Homepage, https://github.com/OpenAdaptAI/openadapt-privacy
Project-URL: Repository, https://github.com/OpenAdaptAI/openadapt-privacy
Author-email: "MLDSAI Inc." <richard@mldsai.com>
License-Expression: MIT
Keywords: automation,gui,phi,pii,privacy,redaction,scrubbing
Classifier: Development Status :: 3 - Alpha
Classifier: Intended Audience :: Developers
Classifier: License :: OSI Approved :: MIT License
Classifier: Programming Language :: Python :: 3
Classifier: Programming Language :: Python :: 3.10
Classifier: Programming Language :: Python :: 3.11
Classifier: Programming Language :: Python :: 3.12
Classifier: Topic :: Security
Classifier: Topic :: Software Development :: Libraries :: Python Modules
Requires-Python: >=3.10
Requires-Dist: pillow>=10.0.0
Requires-Dist: pip>=25.3
Requires-Dist: pydantic>=2.0.0
Provides-Extra: dev
Requires-Dist: pytest-cov>=4.0.0; extra == 'dev'
Requires-Dist: pytest>=7.0.0; extra == 'dev'
Requires-Dist: ruff>=0.1.0; extra == 'dev'
Provides-Extra: presidio
Requires-Dist: presidio-analyzer>=2.2.0; extra == 'presidio'
Requires-Dist: presidio-anonymizer>=2.2.0; extra == 'presidio'
Requires-Dist: presidio-image-redactor>=0.0.50; extra == 'presidio'
Requires-Dist: spacy-transformers>=1.3.0; extra == 'presidio'
Requires-Dist: spacy>=3.7.0; extra == 'presidio'
